__init__.py
adtcls/__init__.py
adtcls/classification.py
adtcls/config/__init__.py
adtcls/config/config.py
adtcls/net/__init__.py
adtcls/net/darknet.py
adtcls/net/yolo.py
adtcls/net/yolo_training.py
adtcls/src/__init__.py
adtcls/src/base_train.py
adtcls/src/classification.py
adtcls/src/evaluate.py
adtcls/src/predict.py
adtcls/src/train.py
adtcls/src/wheel_detect.py
adtcls/src/utils/__init__.py
adtcls/src/utils/callbacks.py
adtcls/src/utils/cfg_utils.py
adtcls/src/utils/dataloader.py
adtcls/src/utils/utils.py
adtcls/src/utils/utils_aug.py
adtcls/src/utils/utils_bbox.py
adtcls/src/utils/utils_fit.py
adtcls/src/utils/utils_metrics.py
adtcls-0.1.0.dist-info/METADATA
adtcls-0.1.0.dist-info/WHEEL
adtcls-0.1.0.dist-info/top_level.txt
adtcls-0.1.0.dist-info/RECORD
